collar/__init__.py
collar/llm.py
collar/main.py
collar/method_settings.py
collar/module_setting.py
collar/system_settings.py
collar/utils.py
collar/core/__init__.py
collar/core/ast/JMapper.py
collar/core/ast/JSource.py
collar/core/ast/PSource.py
collar/core/ast/Source.py
collar/core/ast/__init__.py
collar/core/handler/Handler.py
collar/core/handler/__init__.py
collar/test/__init__.py
collar/test/play_jsource.py
collar_java/.DS_Store
collar_java/dependency-reduced-pom.xml
collar_java/pom.xml
collar_java/.vscode/launch.json
collar_java/.vscode/settings.json
collar_java/src/.DS_Store
collar_java/src/main/.DS_Store
collar_java/src/main/java/.DS_Store
collar_java/src/main/java/ai/.DS_Store
collar_java/src/main/java/ai/d2c/Context.java
collar_java/src/main/java/ai/d2c/JParserHelper.java
collar_java/src/main/java/ai/d2c/JSource.java
collar_java/src/main/java/ai/d2c/Main.java
collar_java/src/main/java/ai/d2c/Util.java
collar_java/target/java_d2c-1.0-SNAPSHOT.jar
collar_java/target/original-java_d2c-1.0-SNAPSHOT.jar
collar_java/target/classes/.DS_Store
collar_java/target/classes/ai/.DS_Store
collar_java/target/classes/ai/d2c/Context.class
collar_java/target/classes/ai/d2c/JParserHelper.class
collar_java/target/classes/ai/d2c/JSource.class
collar_java/target/classes/ai/d2c/Main.class
collar_java/target/classes/ai/d2c/Util.class
collar_java/target/maven-archiver/pom.properties
collar_java/target/maven-status/maven-compiler-plugin/compile/default-compile/createdFiles.lst
collar_java/target/maven-status/maven-compiler-plugin/compile/default-compile/inputFiles.lst
collar_java/target/maven-status/maven-compiler-plugin/testCompile/default-testCompile/createdFiles.lst
collar_java/target/maven-status/maven-compiler-plugin/testCompile/default-testCompile/inputFiles.lst
collar-0.1.16.dist-info/METADATA
collar-0.1.16.dist-info/WHEEL
collar-0.1.16.dist-info/entry_points.txt
collar-0.1.16.dist-info/top_level.txt
collar-0.1.16.dist-info/RECORD
