Metadata-Version: 2.1
Name: collar
Version: 0.1.16
Summary: A Tool to generate comments and code by AI LLM, support to generate code for java, python.the context is from your design document and the code from import modules 
Home-page: https://github.com/dinght-1975/collar_project
Author: Ding Haitao
Author-email: Ding Haitao <dinght1975@gmail.com>
Requires-Python: >=3.8
Requires-Dist: openai
Requires-Dist: jpype1
